concat_remove_library/__init__.py
concat_remove_library/concat_remove.py
concat_remove_library-0.1.0.dist-info/METADATA
concat_remove_library-0.1.0.dist-info/WHEEL
concat_remove_library-0.1.0.dist-info/top_level.txt
concat_remove_library-0.1.0.dist-info/RECORD
